arbitragepy/__init__.py
arbitragepy/arbitrage.py
arbitragepy/enums.py
arbitragepy/exceptions.py
arbitragepy/fee.py
arbitragepy/models.py
arbitragepy/py.typed
arbitragepy/quantity_increment.py
arbitragepy/spread.py
arbitragepy-3.0.0.dist-info/LICENSE
arbitragepy-3.0.0.dist-info/METADATA
arbitragepy-3.0.0.dist-info/WHEEL
arbitragepy-3.0.0.dist-info/RECORD
