Metadata-Version: 2.1
Name: arbitragepy
Version: 3.0.0
Summary: Arbitrage utilities. Has functions that make it easy to work with arbitrage mathematics.
Home-page: https://github.com/astsu-dev/arbitragepy
License: MIT
Author: astsu
Author-email: astsu.dev@gmail.com
Requires-Python: >=3.10,<4.0
Classifier: License :: OSI Approved :: MIT License
Classifier: Programming Language :: Python :: 3
Classifier: Programming Language :: Python :: 3.10
Classifier: Programming Language :: Python :: 3.11
Classifier: Programming Language :: Python :: 3.12
Project-URL: Documentation, https://github.com/astsu-dev/arbitragepy
Project-URL: Repository, https://github.com/astsu-dev/arbitragepy
